ayy/__init__.py
ayy/crawling.py
ayy/db_exp.py
ayy/db_models.py
ayy/dialog.py
ayy/dialogs.py
ayy/func_utils.py
ayy/leggo.py
ayy/memory.py
ayy/prompts.py
ayy/py.typed
ayy/tools.py
ayy/torm.py
ayy/utils.py
ayy-0.1.8.dist-info/METADATA
ayy-0.1.8.dist-info/WHEEL
ayy-0.1.8.dist-info/RECORD
