Metadata-Version: 2.3
Name: ayy
Version: 0.1.8
Summary: Add your description here
Author-email: Hamza Farhan <thehamza96@gmail.com>
Requires-Python: >=3.12
Requires-Dist: anthropic>=0.39.0
Requires-Dist: crawl4ai==0.3.742
Requires-Dist: dill>=0.3.9
Requires-Dist: google-generativeai>=0.8.3
Requires-Dist: instructor>=1.6.3
Requires-Dist: ipykernel>=6.29.5
Requires-Dist: ipywidgets>=8.1.5
Requires-Dist: loguru>=0.7.2
Requires-Dist: moviepy>=1.0.3
Requires-Dist: pydantic>=2.9.2
Requires-Dist: python-dotenv>=1.0.1
Requires-Dist: sqlmodel>=0.0.22
Requires-Dist: tortoise-orm>=0.22.1
Requires-Dist: valkey>=6.0.2
